dj_waanverse_auth/__init__.py
dj_waanverse_auth/admin.py
dj_waanverse_auth/apps.py
dj_waanverse_auth/authentication.py
dj_waanverse_auth/backends.py
dj_waanverse_auth/base_account.py
dj_waanverse_auth/constants.py
dj_waanverse_auth/middleware.py
dj_waanverse_auth/models.py
dj_waanverse_auth/serializers.py
dj_waanverse_auth/urls.py
dj_waanverse_auth/version.py
dj_waanverse_auth/config/__init__.py
dj_waanverse_auth/config/settings.py
dj_waanverse_auth/config/types.py
dj_waanverse_auth/management/__init__.py
dj_waanverse_auth/management/commands/__init__.py
dj_waanverse_auth/management/commands/manage_sessions.py
dj_waanverse_auth/middleware/__init__.py
dj_waanverse_auth/middleware/auth.py
dj_waanverse_auth/migrations/0001_initial.py
dj_waanverse_auth/migrations/0002_accesscode_remove_logincode_account_and_more.py
dj_waanverse_auth/migrations/0003_passkey.py
dj_waanverse_auth/migrations/0004_passkey_name.py
dj_waanverse_auth/migrations/__init__.py
dj_waanverse_auth/services/__init__.py
dj_waanverse_auth/services/token_classes.py
dj_waanverse_auth/services/token_service.py
dj_waanverse_auth/templates/emails/access_code.html
dj_waanverse_auth/templates/emails/login_alert.html
dj_waanverse_auth/templates/emails/login_code.html
dj_waanverse_auth/templates/emails/verify_email.html
dj_waanverse_auth/utils/__init__.py
dj_waanverse_auth/utils/constants.py
dj_waanverse_auth/utils/email_utils.py
dj_waanverse_auth/utils/generators.py
dj_waanverse_auth/utils/login.py
dj_waanverse_auth/utils/security_utils.py
dj_waanverse_auth/utils/serializer_utils.py
dj_waanverse_auth/utils/session_utils.py
dj_waanverse_auth/utils/token_utils.py
dj_waanverse_auth/utils/webauthin.py
dj_waanverse_auth/views/__init__.py
dj_waanverse_auth/views/authorization_views.py
dj_waanverse_auth/views/login_views.py
dj_waanverse_auth/views/passkey_views.py
dj_waanverse_auth/views/signup_views.py
dj_waanverse_auth-2.0.9.dist-info/licenses/LICENSE
dj_waanverse_auth-2.0.9.dist-info/METADATA
dj_waanverse_auth-2.0.9.dist-info/WHEEL
dj_waanverse_auth-2.0.9.dist-info/top_level.txt
dj_waanverse_auth-2.0.9.dist-info/RECORD
