Metadata-Version: 2.4
Name: dj_waanverse_auth
Version: 2.0.9
Summary: A comprehensive Waanverse Labs Inc. internal package for managing user accounts and authentication
Home-page: https://dj-waanverse-auth.waanverse.com/
Author: Waanverse Labs Inc.
Author-email: software@waanverse.com
Maintainer: Khaotungkulmethee Pattawee
Maintainer-email: tawee@waanverse.com
License: Internal Use License
Project-URL: Documentation, https://dj-waanverse-auth.waanverse.com/
Project-URL: Developers, https://www.waanverse.com
Project-URL: Blog, https://www.waanverse.com/blog/
Keywords: django,user accounts,authentication,JWT,MFA
Classifier: Development Status :: 2 - Pre-Alpha
Classifier: Programming Language :: Python :: 3.11
Classifier: License :: Free To Use But Restricted
Classifier: Natural Language :: English
Classifier: Operating System :: OS Independent
Classifier: Framework :: Django :: 5.1
Classifier: Environment :: Web Environment
Classifier: Intended Audience :: Developers
Classifier: Topic :: Software Development :: Libraries :: Python Modules
Classifier: Topic :: Communications :: Email
Classifier: Topic :: Software Development :: Libraries
Classifier: Topic :: Security
Requires-Python: <4.0,>=3.11.9
License-File: LICENSE
Requires-Dist: Django<6.0.0,>=5.1
Requires-Dist: djangorestframework>=3.15.2
Requires-Dist: user-agents>=2.2.0
Requires-Dist: cryptography>=43.0.0
Requires-Dist: requests>=2.32.3
Requires-Dist: PyJWT>=2.9.0
Requires-Dist: mailersend
Requires-Dist: webauthn<3.00,>=2.00
Dynamic: license-file
